more.whytool-0.5-py3.5-nspkg.pth
more/whytool/__init__.py
more/whytool/main.py
more/whytool/tests/test_why_tool.py
more.whytool-0.5.dist-info/DESCRIPTION.rst
more.whytool-0.5.dist-info/METADATA
more.whytool-0.5.dist-info/RECORD
more.whytool-0.5.dist-info/WHEEL
more.whytool-0.5.dist-info/metadata.json
more.whytool-0.5.dist-info/namespace_packages.txt
more.whytool-0.5.dist-info/top_level.txt
