Metadata-Version: 2.0
Name: more.whytool
Version: 0.5
Summary: What code was responsible for generating a view
Home-page: https://github.com/morepath/more.whytool
Author: Martijn Faassen
Author-email: faassen@startifact.com
License: BSD
Keywords: morepath
Platform: UNKNOWN
Classifier: Intended Audience :: Developers
Classifier: License :: OSI Approved :: BSD License
Classifier: Programming Language :: Python :: 2.7
Classifier: Programming Language :: Python :: 3.5
Requires-Dist: dectate
Requires-Dist: morepath (>=0.15)
Requires-Dist: setuptools
Requires-Dist: webob
Provides-Extra: coverage
Requires-Dist: pytest-cov; extra == 'coverage'
Provides-Extra: docs
Requires-Dist: sphinx; extra == 'docs'
Provides-Extra: pep8
Requires-Dist: flake8; extra == 'pep8'
Provides-Extra: test
Requires-Dist: pytest (>=2.9.0); extra == 'test'
Requires-Dist: pytest-remove-stale-bytecode; extra == 'test'
